potee/__init__.py
potee/main.py
potee/testing.py
potee-0.7.dist-info/LICENSE.md
potee-0.7.dist-info/METADATA
potee-0.7.dist-info/WHEEL
potee-0.7.dist-info/top_level.txt
potee-0.7.dist-info/RECORD
