Metadata-Version: 2.1
Name: potee
Version: 0.7
Summary: A package to simplify the process of writing checkers for the Poteet platform
Home-page: https://github.com/PoteeDev/
Author: Ivan Hahanov
Author-email: Ivan Hahanov <ivanhahanov13@gmail.com>
License: MIT
Project-URL: Homepage, https://github.com/PoteeDev/
Project-URL: Bug Tracker, https://github.com/PoteeDev//issues
Keywords: checkers,security,paltform
Classifier: Development Status :: 3 - Alpha
Classifier: Intended Audience :: Developers
Classifier: Topic :: Software Development :: Build Tools
Classifier: License :: OSI Approved :: MIT License
Classifier: Programming Language :: Python :: 3
Classifier: Programming Language :: Python :: 3.8
Classifier: Programming Language :: Python :: 3.9
Classifier: Programming Language :: Python :: 3.10
Requires-Python: >=3.7
License-File: LICENSE.md
